{
	"authors": [
		"quantumde1"
	],
	"copyright": "Copyright © 2025, quantumde1",
	"dependencies": {
		"raylib-d": "~>5.5.1"
	},
	"description": "Engine on Dlang for visual novels",
	"lflags-linux": [
		"-rpath=/usr/lib",
		"-rpath=$$ORIGIN",
		"-build-id=none"
	],
	"lflags-osx": [
		"-rpath",
		"./",
		"-rpath",
		"/opt/local/lib",
		"-build-id=none"
	],
	"lflags-posix": [
		"-L/usr/lib",
		"-L.",
		"-L/opt/local/lib",
		"-L/usr/local/lib",
		"-build-id=none"
	],
	"lflags-windows": [
		"-L./",
		"/Brepro"
	],
	"libs-posix": [
		"raylib",
		"vlc"
	],
	"libs-windows": [
		"raylib",
		"vlc"
	],
	"license": "MIT License",
	"name": "himmel-engine"
}